README.txt
setup.py
disasters/__init__.py
disasters/data.py
disasters/toctree.py
disasters.egg-info/PKG-INFO
disasters.egg-info/SOURCES.txt
disasters.egg-info/dependency_links.txt
disasters.egg-info/requires.txt
disasters.egg-info/top_level.txt