Metadata-Version: 1.0
Name: disasters
Version: 0.0.3
Summary: A python library for my research on disaster news.
Home-page: https://github.com/kedz/disasters
Author: Chris Kedzie
Author-email: kedzie@cs.columbia.edu
License: UNKNOWN
Platform: UNKNOWN
